persistentsql/__init__.py
persistentsql-0.1.2.dist-info/METADATA
persistentsql-0.1.2.dist-info/WHEEL
persistentsql-0.1.2.dist-info/top_level.txt
persistentsql-0.1.2.dist-info/RECORD
