Metadata-Version: 2.4
Name: persistentsql
Version: 0.1.2
Summary: Peristent SQLite Database using S3 on Cloud Workspaces
Author-email: Siddharth Singh <siddharthsingh5010@icloud.com>
Project-URL: Repository, https://github.com/siddharthsingh5010/persistentsql
Requires-Python: >=3.6
Requires-Dist: boto3
Requires-Dist: pandas
Requires-Dist: numpy
